webassets_browserify/__init__.py
webassets_browserify/tests/__init__.py
webassets_browserify/tests/test_browserify.py
webassets_browserify-1.1.0.dist-info/DESCRIPTION.rst
webassets_browserify-1.1.0.dist-info/METADATA
webassets_browserify-1.1.0.dist-info/metadata.json
webassets_browserify-1.1.0.dist-info/RECORD
webassets_browserify-1.1.0.dist-info/top_level.txt
webassets_browserify-1.1.0.dist-info/WHEEL
