Metadata-Version: 2.0
Name: webassets-browserify
Version: 1.1.0
Summary: Browserify filter for webassets
Home-page: https://github.com/renstrom/webassets-browserify
Author: Peter Renström
Author-email: UNKNOWN
License: MIT
Keywords: browserify,webassets,django assets
Platform: UNKNOWN
Classifier: Development Status :: 5 - Production/Stable
Classifier: Intended Audience :: Developers
Classifier: License :: OSI Approved :: MIT License
Classifier: Programming Language :: Python :: 2.7
Classifier: Programming Language :: Python :: 3.3
Classifier: Programming Language :: Python :: 3.4
Requires-Dist: webassets
